Topsis_Arpit/Topsis_Arpit.py
Topsis_Arpit/__init__.py
Topsis_Arpit-0.0.1.dist-info/LICENSE
Topsis_Arpit-0.0.1.dist-info/METADATA
Topsis_Arpit-0.0.1.dist-info/WHEEL
Topsis_Arpit-0.0.1.dist-info/top_level.txt
Topsis_Arpit-0.0.1.dist-info/RECORD
