Metadata-Version: 2.1
Name: Topsis-Arpit
Version: 0.0.1
Summary: A small package that showcases Topsis approach
Home-page: https://github.com/ArpitSingla/TOPSIS-Python.git
Author: Arpit Singla
Author-email: arpitsingla1999@gmail.com
License: UNKNOWN
Download-URL: https://github.com/ArpitSingla/TOPSIS-Python/archive/0.01.tar.gz
Platform: UNKNOWN
Classifier: Programming Language :: Python :: 3
Classifier: License :: OSI Approved :: MIT License
Classifier: Operating System :: OS Independent
Requires-Python: >=3.6
